<contents>
	<group name="助词">
		<content value="ka" name="か"/>
		<content value="ga" name="が/は/も"/>
		<content value="kara" name="から/からは/からも"/>
		<content value="kurai" name="くらい/ぐらい"/>
		<content value="koso" name="こそ"/>
		<content value="dake" name="だけ"/>
		<content value="dakedeha" name="だけでは"/>
		<content value="dakeni" name="だけに"/>
		<content value="de" name="で/では/でも"/>
		<content value="demo" name="でも"/>
		<content value="to" name="と/とは/とも"/>
		<content value="toha" name="とは"/>
		<content value="toka" name="とか"/>
		<content value="ha" name="は"/>
		<content value="bakari" name="ばかり"/>
		<content value="he" name="へ/へは/へも"/>
		<content value="hodo" name="ほど"/>
		<content value="made" name="まで/までは/までも"/>
		<content value="madeni" name="までに/までには/までにも"/>
		<content value="mo" name="も"/>
		<content value="nara" name="なら"/>
		<content value="nado" name="など/なんか"/>
		<content value="nante" name="なんて"/>
		<content value="ni" name="に/には/にも"/>
		<content value="no" name="の"/>
		<content value="nomi" name="のみ"/>
		<content value="sae" name="さえ"/>
		<content value="shika" name="しか"/>
		<content value="sura" name="すら"/>
		<content value="zutsu" name="ずつ"/>
		<content value="ya" name="や"/>
		<content value="yara" name="やら"/>
		<content value="yori" name="より"/>
		<content value="wo" name="を/は/も"/>
		<content value="tte" name="って"/>
	</group>
	<group name="接续助词">
		<content value="ga2" name="が"/>
		<content value="kara2" name="から"/>
		<content value="kedo" name="けれども/けれど/けど"/>
		<content value="tara" name="たら/だら"/>
		<content value="tari" name="たり/だり"/>
		<content value="tutu" name="つつ"/>
		<content value="te" name="て/で"/>
		<content value="teha" name="ては/ちゃ/では/じゃ"/>
		<content value="temo" name="ても/でも"/>
		<content value="tekara" name="てから/でから"/>
		<content value="to2" name="と"/>
		<content value="ba" name="ば"/>
		<content value="na" name="な"/>
		<content value="nagara" name="ながら"/>
		<content value="niha" name="には"/>
		<content value="nimo" name="にも"/>
		<content value="node" name="ので"/>
		<content value="noni" name="のに"/>
		<content value="shi" name="し"/>
	</group>
	<group name="终助词">
		<content value="ka2" name="か"/>
		<content value="kai" name="かい"/>
		<content value="kana" name="かな"/>
		<content value="kedo2" name="けど"/>
		<content value="na2" name="な"/>
		<content value="ne" name="ね/ねえ"/>
		<content value="no2" name="の"/>
		<content value="noni2" name="のに"/>
		<content value="yo" name="よ"/>
		<content value="wa" name="わ"/>
		<content value="wayo" name="わよ"/>
	</group>
</contents>