<basic name="ては/ちゃ/では/じゃ">
	<value type="接续助词">
		<meaning>表示顺接条件。</meaning>
		<usage>
			<value>动词连用形+ては/ちゃ/では/じゃ</value>
			<value>形容词连用形（く）+ては/ちゃ</value>
			<value>形容动词+では/じゃ</value>
			<value>体言+では/じゃ</value>
			<example>
				<jp>今日は風呂に入っ{ては}いけません。</jp>
				<cn>今天不许洗澡。</cn>
			</example>
			<example>
				<jp>今日お酒を飲ん{では}いけません。</jp>
				<cn>今天不许喝酒。</cn>
			</example>
			<example>
				<jp>品物は悪く{ては}いけません。</jp>
				<cn>东西的质量不可以差。</cn>
			</example>
			<example>
				<jp>宿題は明日出さなく{ては}いけませんか。</jp>
				<cn>作业必须明天交吗？</cn>
			</example>
			<example>
				<jp>その時、あの人はあまり有名{では}ありませんでした。</jp>
				<cn>那时，他还不怎么有名。</cn>
			</example>
			<example>
				<jp>勉強は嫌い{では}いけんません。</jp>
				<cn>不能不爱学习。</cn>
			</example>
			<example>
				<jp>ホテルの部屋はあまり静か{じゃ}ありませんでした。</jp>
				<cn>宾馆的房间不是很安静。</cn>
			</example>
			<example>
				<jp>どちらも好き{じゃ}ありません。</jp>
				<cn>哪个都不喜欢。</cn>
			</example>
			<example>
				<jp>ここは学校{では}ありません。</jp>
				<cn>这儿不是学校。</cn>
			</example>
			<example>
				<jp>昨日は金曜日{では}ありませんでした。</jp>
				<cn>昨天不是星期五。</cn>
			</example>
			<example>
				<jp>わたしは日本人{じゃ}ありません。</jp>
				<cn>我不是日本人。</cn>
			</example>
		</usage>
	</value>

</basic>